menus_py/__init__.py
menus_py-1.3.0.dist-info/METADATA
menus_py-1.3.0.dist-info/WHEEL
menus_py-1.3.0.dist-info/licenses/LICENSE
menus_py-1.3.0.dist-info/RECORD
