Metadata-Version: 2.4
Name: menus-py
Version: 1.3.0
Summary: Simple library for creating text-based menus
Author: Kai Fautley
License-File: LICENSE
Classifier: License :: OSI Approved :: GNU General Public License v3 (GPLv3)
Classifier: Operating System :: OS Independent
Classifier: Programming Language :: Python :: 3
Requires-Python: >=3.8
